ftpx/__init__.py
ftpx/ftpx.py
ftpx-0.1.0.dist-info/METADATA
ftpx-0.1.0.dist-info/WHEEL
ftpx-0.1.0.dist-info/top_level.txt
ftpx-0.1.0.dist-info/RECORD
