Metadata-Version: 2.1
Name: ftpx
Version: 0.1.0
Summary: A lib with basic operations of FTP
Home-page: https://gitlab.com/integration_seon/libs/util/ftpx
Author: Paulo Sergio dos Santo Junior
Author-email: paulossjuniort@gmail.com
License: UNKNOWN
Platform: UNKNOWN
Classifier: Programming Language :: Python :: 3
Classifier: License :: OSI Approved :: MIT License
Classifier: Operating System :: OS Independent
